{"authors": [], "date_download": "2019-11-14 08:59:03", "date_modify": "2019-11-14 08:59:03", "date_publish": "2016-05-06 20:06:00", "description": "قصة الأقزام الخضر  كان يا ما كان في قديم الزمان في داخل الغابة صغيرة الحجم و خضراء اللون لديهم قرية صغيرة  و كان لديهم عدة مشاك...", "filename": "2016_05_blog-post_6_1573721943.html", "image_url": "https://2.bp.blogspot.com/-l_qRN-AtX1A/Vy1XGjzrmjI/AAAAAAAAA0I/3EPfrMDlWIoVUjjQqCMKD76Cglu88Cl8QCLcB/w1200-h630-p-k-no-nu/%25D9%2585%25D8%25AF%25D9%258A%25D9%2586%25D8%25A9-%25D8%25A7%25D9%2584%25D8%25A3%25D9%2582%25D8%25B2%25D8%25A7%25D9%2585-%25D9%2584%25D9%258A%25D9%2584%25D9%258A%25D8%25A8%25D9%2588%25D8%25AA-%25D9%2581%25D9%258A-%25D8%25A7%25D9%2584%25D8%25B5%25D9%2591%25D9%258A%25D9%2586-5.png", "language": "ar", "localpath": "/home/motaz/news-please-repo//data/2019/11/14/qisasse.com/2016_05_blog-post_6_1573721943.html", "title": "قصة الأقزام الخضر", "title_page": " قصة الأقزام الخضر ", "title_rss": "NULL", "source_domain": "qisasse.com", "text": "قصة الأقزام الخضر\nكان يا ما كان في قديم الزمان في داخل الغابة صغيرة الحجم و خضراء اللون لديهم قرية صغيرة\nو كان لديهم عدة مشاكل بتلك القرية, مثل مشكل النهر الذي كان دائما يفيض على القرية, و قرروا تصميم مضخة لكي تبطء سرعة النهر التيفكان الحكيم و الزعيم\nوبداو يخططون لهيكل المضخة , فقامو بتخطيطها و كان يجب أن تكون ضخمة و جمعو ألفين شخص\nو قامو بإحضار الخشب من الغابة و بدأوا بالبناء, و بشرو بالبناء و كانو يعملون بكل قوتهم ,و بعد ثلاثة أشهر اكملو بناء المضخة ولما ذهب الزعيم ليتم تدشين وتشغيل المضخة لم ترد الإشتغال\n,فبدأ بتفكير ما هو سبب عدم اشتغال المضخة!!? و من ثم اتذكر أحدهم أنه ترك مطرقة أمام المحرك الذي يدير المضخة قد تكون سقطة و عرقلته ?فذهب فوجد توقعه صحيح و أزال المطرق و شغلوا المضخة\nفأزالو مشكلة النهر وفرح الاقزام حينها كثيرا ....", "url": "https://www.qisasse.com/2016/05/blog-post_6.html"}